terminal_mines/__init__.py
terminal_mines/mines.py
terminal_mines/game_logic/__init__.py
terminal_mines/game_logic/game_model.py
terminal_mines/game_logic/keyboard_listener.py
terminal_mines/game_logic/renderer.py
terminal_mines/game_logic/solver.py
terminal_mines-1.3.dist-info/LICENSE
terminal_mines-1.3.dist-info/METADATA
terminal_mines-1.3.dist-info/WHEEL
terminal_mines-1.3.dist-info/entry_points.txt
terminal_mines-1.3.dist-info/top_level.txt
terminal_mines-1.3.dist-info/RECORD
