Metadata-Version: 2.1
Name: terminal-mines
Version: 1.3
Summary: A command-line clone of Minesweeper in Python
Home-page: https://github.com/JoelEager/terminal-mines
Author: Joel Eager
License: MIT
Platform: UNKNOWN
Classifier: Topic :: Games/Entertainment :: Puzzle Games
Classifier: Environment :: Console
Classifier: Operating System :: POSIX :: Linux
Classifier: Operating System :: MacOS
Classifier: Operating System :: Microsoft :: Windows
Requires-Python: ~=3.4
Requires-Dist: click (==7.0)
